{"answers": [], "options": [["De har varit inriktade enbart på vissa transportsätt.", "De har bortsett från det faktum att resorna blivit allt längre.", "De har gjort jämförelser mellan grupper på ett diskutabelt sätt.", "De har endast kunnat bekräfta sambandet bland dem som faktiskt drabbats."], ["Den behandlar fl er studier.", "Den utesluter rena fallrapporter.", "Den beaktar skillnaden mellan olika resformer.", "Den godtar inte kontrollgruppernas sammansättning. Djup ventrombos"]], "questions": ["15. Vad har enligt texten utgjort ett problem med många av de studier som behandlat sambandet mellan resande och DVT?", "16. Vad skiljer enligt texten den redovisade metaanalysen från tidigare metaanalyser inom fältet?"], "article": "Att resa, t.ex. med fl yget, ökar risken för djup ventrombos,\nblodpropp i vensystemet (DVT). Det rönet presenteras i\nAnnals of Internal Medicine. Att resande, inte minst med\nfl yg, ökar risken för DVT kan knappast komma som en\növerraskning för medicinsk personal, men faktum är att\nden forskning som presenterats inom fältet inte varit entydig. Bidragande till detta är att kontrollgrupperna inte sällan utgjorts av icke-resande individer som utretts på sjukhus med frågeställningen DVT. Man kan på goda grunder\nmisstänka att dessa kontrollgrupper utgjorts av individer\nmed en annan riskprofi l för DVT än resande, vilket gjort\nresultaten svårtolkade.\nFörfattarna till den nu aktuella artikeln har gjort en\nmetaanalys. Med hjälp av databaser som Pubmed, Medline, Embase och Cochrane har man identifi erat studier\ninom fältet.\nDen initiala sökningen resulterade i 1 560 (!) studier.\nAv dessa har den överväldigande majoriteten exkluderats\nav olika anledningar, såsom att det endast rörde sig om\nrena fallrapporter eller att kontrollgrupperna var märkligt sammansatta. Författarna har från de 1 560 studierna\nvaskat fram 14 studier som höll måttet och som således\ningått i analysen. Dessa 14 studier omfattar totalt 4 055\nfall av DVT.\nResultaten visar sammantaget att resande, samtliga\nresformer sammanräknade, fördubblar risken för DVT.\nFörfattarna har därefter exkluderat studier som haft ickeresande individer som utretts för DVT som kontroller.\nDet visade sig då att resande ökade DVT-risken med en\nfaktor 2,8, vilket alltså innebär en närmast tredubblad\nrisk. Tittar man specifi kt på resande med fl yg noterades\natt den relativa risken för DVT steg med 26 procent för\nvarje ytterligare två timmar som resan varade. Samtliga\ntransportsätt sammanräknade, alltså inte bara fl yg, ökade\nDVT-risken med 18 procent för varje ytterligare två timmar som resan varade.\nTvå mindre metaanalyser har tidigare presenterats inom\nområdet resande och DVT-risk. Dessa publicerades för\nett par år sedan och visade på en betydligt svagare koppling mellan resande och risk för DVT än den nu aktuella\nstudien. Dessa två metaanalyser inkluderade dock färre\nstudier än den nu aktuella sammanställningen.\nFörfattarna konstaterar att de egna rönen är de starkaste\nsom hittills presenterats vad gäller kopplingen mellan\nDVT-risk och resande samt magnituden av riskökningen.\nFler studier efterfrågas dock av författarna. Bland annat\nvill de se undersökningar kring i vilken mån DVT-risken\nkan reduceras vid långresor, t.ex. om man är uppe och går\nett par gånger under en längre fl ygresa. Eff ekten av mer\navancerade interventioner, t.ex. att ge farmakologisk profylax mot DVT till riskgrupper som p-pillerätande kvinnor och överviktiga, är också det ett fält där mer forskning\nbehövs.\nAnders Hansen", "id": ""}